exutils/__init__.py
exutils/catch_error.py
exutils/logging.py
exutils-0.1.9.dist-info/licenses/LICENSE
exutils-0.1.9.dist-info/METADATA
exutils-0.1.9.dist-info/WHEEL
exutils-0.1.9.dist-info/top_level.txt
exutils-0.1.9.dist-info/RECORD
