Metadata-Version: 2.4
Name: exutils
Version: 0.1.9
Summary: Common Python utilities, including exception catching decorator.
Author-email: Tsinling <449598613@qq.com>
License: MIT
Project-URL: Homepage, https://github.com/TsinlingLi/exutils
Requires-Python: >=3.6
License-File: LICENSE
Requires-Dist: pandas>=2.0.0
Dynamic: license-file
